Kiwrious/ExampleSubclass.py
Kiwrious/HeartRate.py
Kiwrious/Kiwrious.py
Kiwrious/__init__.py
Kiwrious/service.py
pyKiwrious-0.0.4.dist-info/LICENSE
pyKiwrious-0.0.4.dist-info/METADATA
pyKiwrious-0.0.4.dist-info/WHEEL
pyKiwrious-0.0.4.dist-info/top_level.txt
pyKiwrious-0.0.4.dist-info/RECORD
