Metadata-Version: 2.1
Name: pyKiwrious
Version: 0.0.4
Summary: Support programming with Kiwrious sensor
Author: Team 36
Author-email: hussel@ahlab.org
Keywords: python,sensor
Classifier: Development Status :: 1 - Planning
Classifier: Intended Audience :: Developers
Classifier: Programming Language :: Python :: 3
Classifier: Operating System :: Unix
Classifier: Operating System :: MacOS :: MacOS X
Classifier: Operating System :: Microsoft :: Windows
License-File: LICENSE
Requires-Dist: pyserial
Requires-Dist: numpy
